genoml/__init__.py
genoml/check_dependencies.py
genoml/constants.py
genoml/experimental.py
genoml/main.py
genoml/parse_arguments.py
genoml/utils.py
genoml/experimental/README.md
genoml/experimental/biobank_and_EMR/README.md
genoml/experimental/biobank_and_EMR/UKB_EA.ipynb
genoml/experimental/gwas_utilities/README.md
genoml/experimental/gwas_utilities/get_the_ses.py
genoml/experimental/gwas_utilities/proxy_gwas.py
genoml/experimental/gwas_utilities/reformat_plink2_results.py
genoml/experimental/outlier_detection/README.md
genoml/experimental/outlier_detection/UMAP_Outlier_Detection.ipynb
genoml/experimental/supervised/README.md
genoml/experimental/supervised/test_discrete
genoml/misc/commandline_args.txt
genoml/misc/descriptions.json
genoml/misc/inference_commandline_args.txt
genoml/misc/train_commandline_args.txt
genoml/misc/R/PRSice-mac.R
genoml/misc/R/PRSice.R
genoml/misc/R/checkPrs.R
genoml/misc/R/checkTraining.R
genoml/misc/R/checkValidation.R
genoml/misc/R/dependencies.R
genoml/misc/R/filterSblup.R
genoml/misc/R/io.R
genoml/misc/R/mergeForGenoML.R
genoml/misc/R/prepSblupToScale.R
genoml/misc/R/scaleVariantDoses.R
genoml/misc/R/scaleVariantDoses_training.R
genoml/misc/R/scaleVariantDoses_validation.R
genoml/misc/R/trainCluster.R
genoml/misc/R/trainCont.R
genoml/misc/R/trainDisc.R
genoml/misc/R/tuneCont.R
genoml/misc/R/tuneDisc.R
genoml/misc/R/validateCont.R
genoml/misc/R/validateDisc.R
genoml/steps/__init__.py
genoml/steps/data_prune.py
genoml/steps/model_train.py
genoml/steps/model_tune.py
genoml/steps/model_validate.py
genoml-1.0.4.dist-info/LICENSE
genoml-1.0.4.dist-info/METADATA
genoml-1.0.4.dist-info/WHEEL
genoml-1.0.4.dist-info/entry_points.txt
genoml-1.0.4.dist-info/top_level.txt
genoml-1.0.4.dist-info/RECORD
