Metadata-Version: 2.1
Name: genoml
Version: 1.0.4
Summary: Machine Learning for Genomic
Home-page: https://github.com/genoml/genoml-core
Author: Sayed Hadi Hashemi
Author-email: SayedHadiHashemi@gmail.com
Maintainer: Faraz Faghri
Maintainer-email: faraz.faghri@gmail.com
License: Apache-2.0
Platform: UNKNOWN
Classifier: Programming Language :: Python :: 3 :: Only
Classifier: Development Status :: 4 - Beta
Classifier: License :: OSI Approved :: Apache Software License
Classifier: Operating System :: MacOS :: MacOS X
Classifier: Operating System :: POSIX
Classifier: Topic :: Scientific/Engineering :: Bio-Informatics
Requires-Dist: rpy2
Requires-Dist: docopt
Requires-Dist: pandas-plink
Requires-Dist: numpy
Requires-Dist: requests
Requires-Dist: tqdm
